bp_utils-0.0.1.dist-info/DESCRIPTION.rst
bp_utils-0.0.1.dist-info/METADATA
bp_utils-0.0.1.dist-info/RECORD
bp_utils-0.0.1.dist-info/WHEEL
bp_utils-0.0.1.dist-info/entry_points.txt
bp_utils-0.0.1.dist-info/metadata.json
bp_utils-0.0.1.dist-info/top_level.txt
src/__init__.py
