Metadata-Version: 2.0
Name: bp-utils
Version: 0.0.1
Summary: A set of scripts for Bitbucket Pipelines
Home-page: https://github.com/inteferex/bp-utils
Author: Brett Wandel
Author-email: brett.wandel@interferex.com
License: MIT
Requires-Dist: requests
Provides-Extra: dev
Requires-Dist: check-manifest; extra == 'dev'
Provides-Extra: test
Requires-Dist: coverage; extra == 'test'
